strava_ical/__init__.py
strava_ical/__main__.py
strava_ical/cli.py
strava_ical/cli_strava_offline.py
strava_ical/data.py
strava_ical/ical.py
strava_ical/input.py
strava_ical/py.typed
strava_ical-1.0.0.dist-info/LICENSE
strava_ical-1.0.0.dist-info/METADATA
strava_ical-1.0.0.dist-info/WHEEL
strava_ical-1.0.0.dist-info/entry_points.txt
strava_ical-1.0.0.dist-info/top_level.txt
strava_ical-1.0.0.dist-info/RECORD
