Metadata-Version: 2.1
Name: strava-ical
Version: 1.0.0
Summary: Generate iCalendar with your Strava activities
Author-email: Tomáš Janoušek <tomi@nomi.cz>
License: MIT
Project-URL: Homepage, https://github.com/liskin/strava-ical
Project-URL: Release Notes, https://github.com/liskin/strava-ical/releases
Project-URL: Issues, https://github.com/liskin/strava-ical/issues
Project-URL: CI, https://github.com/liskin/strava-ical/actions
Project-URL: Donations (GitHub), https://github.com/sponsors/liskin
Project-URL: Donations (PayPal), https://www.paypal.me/lisknisi/5EUR
Classifier: Development Status :: 5 - Production/Stable
Classifier: Environment :: Console
Classifier: License :: OSI Approved :: MIT License
Classifier: Operating System :: OS Independent
Classifier: Programming Language :: Python :: 3.8
Classifier: Programming Language :: Python :: 3.9
Classifier: Programming Language :: Python :: 3.10
Classifier: Programming Language :: Python :: 3.11
Classifier: Programming Language :: Python :: 3.12
Classifier: Topic :: Utilities
Requires-Python: ~=3.8
License-File: LICENSE
Requires-Dist: click ~=8.0
Requires-Dist: icalendar >=5.0.2
Requires-Dist: platformdirs >=2.1
Requires-Dist: python-dateutil >=2.7
Requires-Dist: importlib-metadata ; python_version < "3.10"
Provides-Extra: dev
Requires-Dist: build >=0.7 ; extra == 'dev'
Requires-Dist: flake8 >=3.7 ; extra == 'dev'
Requires-Dist: isort >=5.0 ; extra == 'dev'
Requires-Dist: mypy >=1.0 ; extra == 'dev'
Requires-Dist: prysk ==0.17.0 ; extra == 'dev'
Requires-Dist: twine ; extra == 'dev'
Requires-Dist: types-python-dateutil ; extra == 'dev'
Provides-Extra: strava
Requires-Dist: strava-offline ~=1.0 ; extra == 'strava'
Provides-Extra: test
Requires-Dist: pytest ; extra == 'test'
